[
    {
        "id_address": 1,
        "id_recipient": 1,
        "address": "",
        "status": ""
    },
    {
        "id_address": 2,
        "id_recipient": 1,
        "address": "",
        "status": ""
    },
    {
        "id_address": 3,
        "id_recipient": 2,
        "address": "",
        "status": ""
    },
    {
        "id_address": 4,
        "id_recipient": 3,
        "address": "",
        "status": ""
    },
    {
        "id_address": 5,
        "id_recipient": 4,
        "address": "",
        "status": ""
    },
    {
        "id_address": 6,
        "id_recipient": 7,
        "address": "Школьная",
        "status": "Home"
    },
    {
        "id_address": 7,
        "id_recipient": 7,
        "address": "Школьная",
        "status": "Home"
    },
    {
        "id_address": 8,
        "id_recipient": 7,
        "address": "Школьная",
        "status": "Home"
    },
    {
        "id_address": 9,
        "id_recipient": 8,
        "address": "Школьная",
        "status": "Work"
    },
    {
        "id_address": 10,
        "id_recipient": 11,
        "address": "Это адрес контакта",
        "status": "Домашний"
    },
    {
        "id_address": 11,
        "id_recipient": 11,
        "address": "Это адрес контакта",
        "status": "Домашний"
    },
    {
        "id_address": 12,
        "id_recipient": 11,
        "address": "Это адрес контакта",
        "status": "Домашний"
    },
    {
        "id_address": 13,
        "id_recipient": 11,
        "address": "Это адрес контакта",
        "status": "Домашний"
    },
    {
        "id_address": 14,
        "id_recipient": 11,
        "address": "Это адрес контакта",
        "status": "Домашний"
    },
    {
        "id_address": 15,
        "id_recipient": 11,
        "address": "Это адрес контакта",
        "status": "Домашний"
    },
    {
        "id_address": 16,
        "id_recipient": 4,
        "address": "Крутая",
        "status": "Home"
    },
    {
        "id_address": 17,
        "id_recipient": 11,
        "address": "Это адрес контакта",
        "status": "Домашний"
    },
    {
        "id_address": 18,
        "id_recipient": 11,
        "address": "Это адрес контакта",
        "status": "Домашний"
    },
    {
        "id_address": 19,
        "id_recipient": 11,
        "address": "Это адрес контакта",
        "status": "Домашний"
    },
    {
        "id_address": 20,
        "id_recipient": 11,
        "address": "Это адрес контакта",
        "status": "Домашний"
    }
]